adobe/__init__.py
adobe/pdfservices/__init__.py
adobe/pdfservices/operation/__init__.py
adobe/pdfservices/operation/pdf_services.py
adobe/pdfservices/operation/pdf_services_job.py
adobe/pdfservices/operation/pdf_services_job_status.py
adobe/pdfservices/operation/pdf_services_job_status_response.py
adobe/pdfservices/operation/pdf_services_media_type.py
adobe/pdfservices/operation/pdf_services_response.py
adobe/pdfservices/operation/region.py
adobe/pdfservices/operation/auth/__init__.py
adobe/pdfservices/operation/auth/credentials.py
adobe/pdfservices/operation/auth/service_principal_credentials.py
adobe/pdfservices/operation/config/__init__.py
adobe/pdfservices/operation/config/client_config.py
adobe/pdfservices/operation/config/notifier/__init__.py
adobe/pdfservices/operation/config/notifier/callback_notifier_data.py
adobe/pdfservices/operation/config/notifier/notifier_config.py
adobe/pdfservices/operation/config/notifier/notifier_data.py
adobe/pdfservices/operation/config/notifier/notifier_type.py
adobe/pdfservices/operation/config/proxy/__init__.py
adobe/pdfservices/operation/config/proxy/proxy_authentication_credentials.py
adobe/pdfservices/operation/config/proxy/proxy_scheme.py
adobe/pdfservices/operation/config/proxy/proxy_server_config.py
adobe/pdfservices/operation/config/proxy/username_password_credentials.py
adobe/pdfservices/operation/exception/__init__.py
adobe/pdfservices/operation/exception/exceptions.py
adobe/pdfservices/operation/internal/__init__.py
adobe/pdfservices/operation/internal/exceptions.py
adobe/pdfservices/operation/internal/execution_context.py
adobe/pdfservices/operation/internal/pdf_services_helper.py
adobe/pdfservices/operation/internal/api/__init__.py
adobe/pdfservices/operation/internal/api/pdf_services_api.py
adobe/pdfservices/operation/internal/api/storage_api.py
adobe/pdfservices/operation/internal/api/dto/__init__.py
adobe/pdfservices/operation/internal/api/dto/request/__init__.py
pdfservices_sdk-4.2.0.dist-info/LICENSE.md
pdfservices_sdk-4.2.0.dist-info/METADATA
pdfservices_sdk-4.2.0.dist-info/WHEEL
pdfservices_sdk-4.2.0.dist-info/top_level.txt
pdfservices_sdk-4.2.0.dist-info/RECORD
