Metadata-Version: 2.1
Name: pdfservices-sdk
Version: 4.2.0
Summary: Adobe PDFServices Client Library
Home-page: https://www.adobe.com/go/pdftoolsapi_doc
Author: Adobe Acrobat Services
Author-email: extractapi@adobe.com
License: Apache2
Classifier: Development Status :: 5 - Production/Stable
Classifier: Intended Audience :: Developers
Classifier: Programming Language :: Python :: 3.12
Classifier: License :: OSI Approved :: Apache Software License
Classifier: Operating System :: OS Independent
Requires-Python: >=3.10
License-File: LICENSE.md
